outpost_sdk/__init__.py
outpost_sdk/_hooks/__init__.py
outpost_sdk/_hooks/registration.py
outpost_sdk/_hooks/sdkhooks.py
outpost_sdk/_hooks/types.py
outpost_sdk/_version.py
outpost_sdk/basesdk.py
outpost_sdk/destinations.py
outpost_sdk/errors/__init__.py
outpost_sdk/errors/apierror.py
outpost_sdk/errors/badrequest_error.py
outpost_sdk/errors/internalservererror.py
outpost_sdk/errors/listtenantsop.py
outpost_sdk/errors/no_response_error.py
outpost_sdk/errors/notfound_error.py
outpost_sdk/errors/outposterror.py
outpost_sdk/errors/ratelimited_error.py
outpost_sdk/errors/responsevalidationerror.py
outpost_sdk/errors/timeout_error.py
outpost_sdk/errors/unauthorized_error.py
outpost_sdk/events.py
outpost_sdk/health.py
outpost_sdk/httpclient.py
outpost_sdk/models/__init__.py
outpost_sdk/models/awskinesisconfig.py
outpost_sdk/models/awskinesiscredentials.py
outpost_sdk/models/awss3config.py
outpost_sdk/models/awss3credentials.py
outpost_sdk/models/awssqsconfig.py
outpost_sdk/models/awssqscredentials.py
outpost_sdk/models/azureservicebusconfig.py
outpost_sdk/models/azureservicebuscredentials.py
outpost_sdk/models/createtenantdestinationop.py
outpost_sdk/models/deletetenantdestinationop.py
outpost_sdk/models/deletetenantop.py
outpost_sdk/models/deliveryattempt.py
outpost_sdk/models/destination.py
outpost_sdk/models/destinationawskinesis.py
outpost_sdk/models/destinationawss3.py
outpost_sdk/models/destinationawssqs.py
outpost_sdk/models/destinationazureservicebus.py
outpost_sdk/models/destinationcreate.py
outpost_sdk/models/destinationcreateawskinesis.py
outpost_sdk/models/destinationcreateawss3.py
outpost_sdk/models/destinationcreateawssqs.py
outpost_sdk/models/destinationcreateazureservicebus.py
outpost_sdk/models/destinationcreategcppubsub.py
outpost_sdk/models/destinationcreatehookdeck.py
outpost_sdk/models/destinationcreaterabbitmq.py
outpost_sdk/models/destinationcreatewebhook.py
outpost_sdk/models/destinationgcppubsub.py
outpost_sdk/models/destinationhookdeck.py
outpost_sdk-0.5.0.dist-info/METADATA
outpost_sdk-0.5.0.dist-info/WHEEL
outpost_sdk-0.5.0.dist-info/RECORD
